{
  "repo": "forge-chain-mempool-lab",
  "language": "C",
  "category": "Blockchain tooling",
  "goal": "Implement a C blockchain tooling project for mempool format conversion, using round-trip fixtures and lossless normalization checks.",
  "weights": {
    "signal": 4,
    "slack": 1,
    "confidence": 1,
    "drag": 4
  },
  "thresholds": {
    "ship": 169,
    "watch": 119
  },
  "properties": [
    "raising signal cannot reduce score",
    "raising drag cannot improve score",
    "lane labels must match configured thresholds",
    "golden fixture ids must remain unique"
  ],
  "fixture_files": [
    "fixtures/golden/scoreboard.csv",
    "fixtures/golden/lane-matrix.csv",
    "fixtures/fuzz/mutations.csv",
    "fixtures/fuzz/boundary-cases.jsonl"
  ]
}
